{
  "document_id": "OTHER-EMAILS-3-20250526",
  "document_type": [
    "Email_Communication"
  ],
  "agency": [
    "OTHER"
  ],
  "case_number": "HS-FEMA-02430-2024",
  "created_date": "2025-05-26",
  "file_info": {
    "original_filename": "EMAILS-3.pdf",
    "file_size": 3266201,
    "file_hash": "91a24b3401b5f75867836f2b642bbea55e6bb9a637371acd0d7590dd2455bf89",
    "mime_type": "application/pdf"
  },
  "processing_info": {
    "processed_date": "2025-05-26T20:48:55.129405",
    "validation_status": "Validated",
    "validation_errors": [
      "TEXT_EXTRACTION_FAILED"
    ]
  },
  "audit_trail": [
    {
      "timestamp": "2025-05-26T20:48:55.129405",
      "action": "Created",
      "user": "Max",
      "details": "Initial metadata creation"
    }
  ]
}