{
  "document_id": "FEMA-MEINDL-FEMA Informal Intake Form-09-03-24-20250526",
  "document_type": [
    "Other"
  ],
  "agency": [
    "FEMA"
  ],
  "case_number": "HS-FEMA-02430-2024",
  "created_date": "2025-05-26",
  "file_info": {
    "original_filename": "MEINDL-FEMA Informal Intake Form-09-03-24.pdf",
    "file_size": 343711,
    "file_hash": "a3a385fa51aea1408bc3e805d77d6ce80bb5e3744ec371e426efcb353642aec3",
    "mime_type": "application/pdf"
  },
  "processing_info": {
    "processed_date": "2025-05-26T20:49:12.490393",
    "validation_status": "Validated",
    "validation_errors": [
      "TEXT_EXTRACTION_FAILED"
    ]
  },
  "audit_trail": [
    {
      "timestamp": "2025-05-26T20:49:12.490393",
      "action": "Created",
      "user": "Max",
      "details": "Initial metadata creation"
    }
  ]
}